setup.py
src/aioservices/__init__.py
src/aioservices/client.py
src/aioservices/service.py
src/aioservices.egg-info/PKG-INFO
src/aioservices.egg-info/SOURCES.txt
src/aioservices.egg-info/dependency_links.txt
src/aioservices.egg-info/top_level.txt
src/aioservices.egg-info/zip-safe