Metadata-Version: 1.1
Name: aioservices
Version: 0.1.0
Summary: Python 3 asyncio microservices framework
Home-page: UNKNOWN
Author: Roman Mogilatov
Author-email: rmogilatov@gmail.com
License: BSD New
Keywords: asyncio,microservice,framework
Platform: any
Classifier: Development Status :: 2 - Pre-Alpha
Classifier: Intended Audience :: Developers
Classifier: License :: OSI Approved :: BSD License
Classifier: Operating System :: OS Independent
Classifier: Programming Language :: Python :: 3
Classifier: Programming Language :: Python :: 3.6
Classifier: Programming Language :: Python :: Implementation :: CPython
Classifier: Framework :: AsyncIO
Classifier: Topic :: Software Development
Classifier: Topic :: Software Development :: Libraries
Classifier: Topic :: Software Development :: Libraries :: Python Modules
